simba_sdk/__init__.py
simba_sdk/chat.py
simba_sdk/client.py
simba_sdk/document.py
simba_sdk/embed.py
simba_sdk/parser.py
simba_sdk/retrieve.py
simba_client-0.3.0.dist-info/METADATA
simba_client-0.3.0.dist-info/WHEEL
simba_client-0.3.0.dist-info/RECORD
