Metadata-Version: 2.1
Name: simba-client
Version: 0.3.0
Summary: Python client for the Simba Knowledge management System
Home-page: https://github.com/GitHamza0206/simba-client
Author: Hamza Zerouali
Author-email: zeroualihamza0206@gmail.com
Requires-Python: >=3.8,<4.0
Classifier: Development Status :: 4 - Beta
Classifier: Intended Audience :: Developers
Classifier: License :: OSI Approved :: MIT License
Classifier: Programming Language :: Python :: 3
Classifier: Programming Language :: Python :: 3.8
Classifier: Programming Language :: Python :: 3.9
Classifier: Programming Language :: Python :: 3.10
Classifier: Programming Language :: Python :: 3.11
Classifier: Programming Language :: Python :: 3.12
Classifier: Programming Language :: Python :: 3.13
Requires-Dist: pydantic (>=2.0.0,<3.0.0)
Requires-Dist: requests (>=2.28.0,<3.0.0)
Requires-Dist: urllib3 (>=2.0.0,<3.0.0)
Project-URL: Documentation, https://simba-client.readthedocs.io
Project-URL: Repository, https://github.com/GitHamza0206/simba-client
